Workbook

Sheet ReadMe
A1: Project 1 — Biodiversity and Medicinal Agroforestry: Financial Model (v2)
A2: Katlabodi Integrated Village Development Project · Annex D · Discussion draft, September 2026
A4: Purpose | B4: Ten-year financial view of the Project 1 demonstration site (about 5 ha plus boundary bamboo) at Katlabodi, the hub for the Katol block cluster.
A5: Source | B5: All capital, operating and revenue figures are carried over unchanged from Project1_Agroforestry__Finances.xlsx (Ayurvan Foundation working estimate). Only the calculation structure has been corrected.
A6: Correction 1 | B6: Original row 47 used =SUM(C1:C46), which added the year numbers, the capital cost (twice in Year 1) and the O&M line into revenue. Revenue now sums species rows only.
A7: Correction 2 | B7: Original "Gross income" (row 53) subtracted O&M that had already been added to revenue, so O&M was never deducted in Years 2–10. O&M is now deducted once.
A8: Correction 3 | B8: Capital cost is now shown in the cash flow, with cumulative position and payback year.
A9: Funding decision | B9: Capital cost of Year 1 is sought within the CSR grant (budget line D1). The Year-1 operating shortfall is shown as D2.
A10: Drought stress test | B10: Sheet "Drought" applies illustrative yield losses in one drought year. Loss rates are UrjaGram assumptions for testing resilience, not observed data.
A11: Legend | B11: Blue text = hard-coded input from source estimate · Black = formula · Green = link to another sheet · Yellow fill = assumption to be validated or line to be filled.
A12: Open points | B12: (1) Basis for nursery revenue of ₹24.75 lakh in Year 1 to be documented. (2) Capex line "Staff and Workers" and Year-1 O&M may overlap — to be confirmed. (3) Candidate species (lemongrass, safed musli, arjuna) not yet costed. (4) Year-2 operating shortfall falls after the grant period.

Sheet Inputs
A1: Inputs and assumptions
A3: Parameter | B3: Value | C3: Unit | D3: Source / note
A4: Area — woody medicinal species | B4: 0.5 | C4: ha | D4: Source estimate (Ayurvan)
A5: Area — fruit-bearing species | B5: 0.5 | C5: ha | D5: Source estimate
A6: Area — fodder grass | B6: 2 | C6: ha | D6: Source estimate
A7: Area — medicinal shrubs | B7: 1 | C7: ha | D7: Source estimate
A8: Area — nursery | B8: 1 | C8: ha | D8: Source estimate
A9: Bamboo along periphery | B9: 600 | C9: trees | D9: Source estimate
A10: Nursery revenue, Year 1 | B10: 2475000 | C10: ₹ | D10: Source estimate — basis to be documented
A11: Nursery revenue growth per year | B11: 0.05 | C11: % | D11: Source estimate
A12: Drought year (1–10) | B12: 2 | C12: year | D12: Stress-test lever; Year 2 = first full year after the 2026 drought
A13: Drought yield loss — woody medicinal and fruit | B13: 0.3 | C13: % | D13: UrjaGram assumption for stress test
A14: Drought yield loss — fodder grass | B14: 0.6 | C14: % | D14: UrjaGram assumption for stress test
A15: Drought yield loss — medicinal shrubs | B15: 0.5 | C15: % | D15: UrjaGram assumption for stress test
... A17: Drought yield loss — bamboo | B17: 0.1 | C17: % | D17: UrjaGram assumption for stress test

Sheet Capex
A1: Capital expenditure — Year 1 (₹)
A2: Sought within the CSR grant, budget line D1
A3: # | B3: Item | C3: Amount (₹) | D3: Note
A4: 1 | B4: Site Preparation, levelling, improvement of soil | C4: 950000
A5: 2 | B5: Potting and soil preparation area development | C5: 450000
A6: 3 | B6: Seeds, Saplings, planting material & containers | C6: 550000
A7: 4 | B7: Shade-net / insect-proof nursery structures | C7: 1675000
A8: 5 | B8: Nursery and Plantation Activities maintenance | C8: 350000
A9: 6 | B9: Fencing boundary and gate | C9: 1800000
A10: 7 | B10: Water Source (Bore well) | C10: 1600000
A11: 8 | B11: Soil and manure | C11: 550000
A12: 9 | B12: Construction of Over Water tank and Drip irrigation facility | C12: 1850000
A13: 10 | B13: Construction of Office, staff room and toilets | C13: 850000
A14: 11 | B14: Machines and equipments (2 Nos) | C14: 1450000
A15: 12 | B15: Signages, boards | C15: 550000
A16: 13 | B16: Provision of electricity or solar power system | C16: 1650000
A17: 14 | B17: Staff and Workers | C17: 1956000 | D17: Establishment-year staffing; confirm no overlap with Year-1 O&M
A18: 15 | B18: Contingencies | C18: 275000
B19: Total capital expenditure | C19: =SUM(C4:C18) -> 16506000

Sheet Revenue
A1: Revenue by species — base case (₹)
A2: Species figures carried over from source estimate
A3: Group | B3: Species | C3: Year 1 | D3: Year 2 | E3: Year 3 | F3: Year 4 | G3: Year 5 | H3: Year 6 | I3: Year 7 | J3: Year 8 | K3: Year 9 | L3: Year 10 | M3: 10-year total
A4: Woody medicinal (0.5 ha) | B4: Amla | C4: 0 | D4: 0 | E4: 30000 | F4: 50000 | G4: 75000 | H4: 90000 | I4: 100000 | J4: 110000 | K4: 120000 | L4: 130000 | M4: =SUM(C4:L4) -> 705000
B5: Bael | C5: 0 | D5: 0 | E5: 20000 | F5: 35000 | G5: 50000 | H5: 65000 | I5: 75000 | J5: 85000 | K5: 95000 | L5: 105000 | M5: =SUM(C5:L5) -> 530000
B6: Hirda | C6: 0 | D6: 0 | E6: 0 | F6: 15000 | G6: 30000 | H6: 45000 | I6: 60000 | J6: 75000 | K6: 90000 | L6: 105000 | M6: =SUM(C6:L6) -> 420000
B7: Moringa | C7: 40000 | D7: 50000 | E7: 60000 | F7: 70000 | G7: 75000 | H7: 80000 | I7: 85000 | J7: 90000 | K7: 95000 | L7: 100000 | M7: =SUM(C7:L7) -> 745000
A8: Fruit-bearing (0.5 ha) | B8: Mango | C8: 0 | D8: 0 | E8: 110000 | F8: 232000 | G8: 365000 | H8: 479000 | I8: 570000 | J8: 633000 | K8: 702000 | L8: 776000 | M8: =SUM(C8:L8) -> 3867000
B9: Sitaphal | C9: 0 | D9: 0 | E9: 198000 | F9: 347000 | G9: 511000 | H9: 613000 | I9: 724000 | J9: 802000 | K9: 886000 | L9: 931000 | M9: =SUM(C9:L9) -> 5012000
B10: Mulberry | C10: 0 | D10: 88000 | E10: 185000 | F10: 259000 | G10: 306000 | H10: 357000 | I10: 375000 | J10: 394000 | K10: 414000 | L10: 434000 | M10: =SUM(C10:L10) -> 2812000
B11: Lemon | C11: 0 | D11: 243000 | E11: 509000 | F11: 713000 | G11: 842000 | H11: 983000 | I11: 1032000 | J11: 1083000 | K11: 1138000 | L11: 1195000 | M11: =SUM(C11:L11) -> 7738000
B12: Jamun | C12: 0 | D12: 0 | E12: 0 | F12: 116000 | G12: 243000 | H12: 383000 | I12: 503000 | J12: 598000 | K12: 702000 | L12: 776000 | M12: =SUM(C12:L12) -> 3321000
B13: Ber | C13: 0 | D13: 0 | E13: 132000 | F13: 232000 | G13: 340000 | H13: 434000 | I13: 509000 | J13: 563000 | K13: 591000 | L13: 621000 | M13: =SUM(C13:L13) -> 3422000
B14: Karvanda | C14: 0 | D14: 126000 | E14: 265000 | F14: 370000 | G14: 438000 | H14: 511000 | I14: 536000 | J14: 563000 | K14: 591000 | L14: 621000 | M14: =SUM(C14:L14) -> 4021000
A15: Fodder grass (2 ha) | B15: Fodder grass | C15: 252000 | D15: 378000 | E15: 396900 | F15: 416700 | G15: 437580 | H15: 459360 | I15: 482400 | J15: 506520 | K15: 531900 | L15: 558540 | M15: =SUM(C15:L15) -> 4419900
A16: Medicinal shrubs (1 ha) | B16: Ashwagandha | C16: 11700 | D16: 12300 | E16: 12900 | F16: 14200 | G16: 14900 | H16: 15700 | I16: 16400 | J16: 17200 | K16: 18100 | L16: 19000 | M16: =SUM(C16:L16) -> 152400
B17: Kalmegh | C17: 9100 | D17: 9600 | E17: 10100 | F17: 11100 | G17: 11700 | H17: 12200 | I17: 12800 | J17: 13500 | K17: 14100 | L17: 14900 | M17: =SUM(C17:L17) -> 119100
B18: Gulab | C18: 12000 | D18: 12600 | E18: 13200 | F18: 14600 | G18: 15300 | H18: 16100 | I18: 16900 | J18: 17700 | K18: 18600 | L18: 19500 | M18: =SUM(C18:L18) -> 156500
B19: Aloe Vera | C19: 0 | D19: 31500 | E19: 66200 | F19: 69400 | G19: 72900 | H19: 76500 | I19: 80300 | J19: 84300 | K19: 88500 | L19: 92900 | M19: =SUM(C19:L19) -> 662500
B20: Brahmi | C20: 20000 | D20: 21000 | E20: 22100 | F20: 23200 | G20: 24400 | H20: 25600 | I20: 26900 | J20: 28200 | K20: 29600 | L20: 31100 | M20: =SUM(C20:L20) -> 252100
A21: Bamboo — 600 trees on periphery | B21: Bamboo | C21: 0 | D21: 0 | E21: 0 | F21: 0 | G21: 0 | H21: 300000 | I21: 300000 | J21: 300000 | K21: 300000 | L21: 300000 | M21: =SUM(C21:L21) -> 1500000
A22: Nursery (1 ha) | B22: Planting material sales | C22: =Inputs!$B$10 -> 2475000 | D22: =C22*(1+Inputs!$B$11) -> 2598750 | E22: =D22*(1+Inputs!$B$11) -> 2728687.5 | F22: =E22*(1+Inputs!$B$11) -> 2865121.9 | G22: =F22*(1+Inputs!$B$11) -> 3008378 | H22: =G22*(1+Inputs!$B$11) -> 3158796.9 | I22: =H22*(1+Inputs!$B$11) -> 3316736.7 | J22: =I22*(1+Inputs!$B$11) -> 3482573.5 | K22: =J22*(1+Inputs!$B$11) -> 3656702.2 | L22: =K22*(1+Inputs!$B$11) -> 3839537.3 | M22: =SUM(C22:L22) -> 31130284
A23: Total revenue | C23: =SUM(C4:C22) -> 2819800 | D23: =SUM(D4:D22) -> 3570750 | E23: =SUM(E4:E22) -> 4759087.5 | F23: =SUM(F4:F22) -> 5853321.9 | G23: =SUM(G4:G22) -> 6860158 | H23: =SUM(H4:H22) -> 8104256.9 | I23: =SUM(I4:I22) -> 8821436.7 | J23: =SUM(J4:J22) -> 9445993.5 | ... M23: =SUM(M4:M22) -> 70985784

Sheet CashFlow
A1: Cash flow — base case (₹)
A2: Undiscounted; capital cost in Year 1
A3: Line | C3: Year 1 | D3: Year 2 | E3: Year 3 | F3: Year 4 | G3: Year 5 | H3: Year 6 | I3: Year 7 | J3: Year 8 | K3: Year 9 | L3: Year 10 | M3: 10-year total
A4: Revenue | C4: =Revenue!C23 -> 2819800 | D4: =Revenue!D23 -> 3570750 | E4: =Revenue!E23 -> 4759087.5 | F4: =Revenue!F23 -> 5853321.9 | G4: =Revenue!G23 -> 6860158 | H4: =Revenue!H23 -> 8104256.9 | I4: =Revenue!I23 -> 8821436.7 | J4: =Revenue!J23 -> 9445993.5 | ... L4: =Revenue!L23 -> 10669477 | M4: =SUM(C4:L4) -> 70985784
A5: Operation and maintenance | C5: 4460000 | D5: 4500000 | E5: 4500000 | F5: 4500000 | G5: 4500000 | H5: 4700000 | I5: 4700000 | J5: 4700000 | K5: 4700000 | L5: 4700000 | M5: =SUM(C5:L5) -> 45960000
A6: Operating surplus / (shortfall) | C6: =C4-C5 -> -1640200 | D6: =D4-D5 -> -929250 | E6: =E4-E5 -> 259087.5 | F6: =F4-F5 -> 1353321.9 | G6: =G4-G5 -> 2360158 | H6: =H4-H5 -> 3404256.9 | I6: =I4-I5 -> 4121436.7 | J6: =J4-J5 -> 4745993.5 | ... L6: =L4-L5 -> 5969477.3 | M6: =SUM(C6:L6) -> 25025784
A7: Capital expenditure | C7: =Capex!$C$19 -> 16506000 | D7: 0 | E7: 0 | F7: 0 | G7: 0 | H7: 0 | I7: 0 | J7: 0 | K7: 0 | L7: 0 | M7: =SUM(C7:L7) -> 16506000
A8: Net cash flow | C8: =C6-C7 -> -18146200 | D8: =D6-D7 -> -929250 | E8: =E6-E7 -> 259087.5 | F8: =F6-F7 -> 1353321.9 | G8: =G6-G7 -> 2360158 | H8: =H6-H7 -> 3404256.9 | I8: =I6-I7 -> 4121436.7 | J8: =J6-J7 -> 4745993.5 | ... L8: =L6-L7 -> 5969477.3 | M8: =SUM(C8:L8) -> 8519784
A9: Cumulative net cash flow | C9: =C8 -> -18146200 | D9: =C9+D8 -> -19075450 | E9: =D9+E8 -> -18816362 | F9: =E9+F8 -> -17463041 | G9: =F9+G8 -> -15102883 | H9: =G9+H8 -> -11698626 | I9: =H9+I8 -> -7577189.1 | J9: =I9+J8 -> -2831195.5 | K9: =J9+K8 -> 2550306.7 | L9: =K9+L8 -> 8519784
A10: Payback flag (helper) | C10: =IF(C9>=0,1,"") | D10: =IF(AND(D9>=0,C9<0),2,"") | E10: =IF(AND(E9>=0,D9<0),3,"") | F10: =IF(AND(F9>=0,E9<0),4,"") | G10: =IF(AND(G9>=0,F9<0),5,"") | H10: =IF(AND(H9>=0,G9<0),6,"") | I10: =IF(AND(I9>=0,H9<0),7,"") | J10: =IF(AND(J9>=0,I9<0),8,"") | K10: =IF(AND(K9>=0,J9<0),9,"") -> 9 | L10: =IF(AND(L9>=0,K9<0),10,"")
A12: Key results
A13: Year-1 operating shortfall (grant line D2) | C13: =MAX(0,-C6) -> 1640200
A14: Year-2 operating shortfall (after grant period) | C14: =MAX(0,-D6) -> 929250
A15: First year with operating surplus | C15: =IF(COUNTIF(C6:L6,">0")=0,"None within 10 years",INDEX(C3:L3,MATCH(TRUE(),INDEX(C6:L6>0,0),0))) -> Year 3
A16: 10-year operating surplus (before capital cost) | C16: =M6 -> 25025784
A17: 10-year net position (after capital cost) | C17: =M8 -> 8519784
A18: Payback year (capital cost recovered) | C18: =IF(COUNT(C10:L10)=0,"Beyond Year 10",MIN(C10:L10)) -> 9

Sheet Drought
A1: Drought stress test (₹)
A2: One drought year (Inputs!B12) with group-wise yield losses (Inputs!B13:B17); all other years as base case
A3: Line | C3: Year 1 | D3: Year 2 | E3: Year 3 | F3: Year 4 | G3: Year 5 | H3: Year 6 | I3: Year 7 | J3: Year 8 | K3: Year 9 | L3: Year 10 | M3: 10-year total
A4: Woody medicinal | C4: =SUM(Revenue!C4:C7)*(1-IF(1=Inputs!$B$12,Inputs!$B$13,0)) -> 40000 | D4: =SUM(Revenue!D4:D7)*(1-IF(2=Inputs!$B$12,Inputs!$B$13,0)) -> 35000 | E4: =SUM(Revenue!E4:E7)*(1-IF(3=Inputs!$B$12,Inputs!$B$13,0)) -> 110000 | F4: =SUM(Revenue!F4:F7)*(1-IF(4=Inputs!$B$12,Inputs!$B$13,0)) -> 170000 | G4: =SUM(Revenue!G4:G7)*(1-IF(5=Inputs!$B$12,Inputs!$B$13,0)) -> 230000 | H4: =SUM(Revenue!H4:H7)*(1-IF(6=Inputs!$B$12,Inputs!$B$13,0)) -> 280000 | I4: =SUM(Revenue!I4:I7)*(1-IF(7=Inputs!$B$12,Inputs!$B$13,0)) -> 320000 | J4: =SUM(Revenue!J4:J7)*(1-IF(8=Inputs!$B$12,Inputs!$B$13,0)) -> 360000 | K4: =SUM(Revenue!K4:K7)*(1-IF(9=Inputs!$B$12,Inputs!$B$13,0)) -> 400000 | L4: =SUM(Revenue!L4:L7)*(1-IF(10=Inputs!$B$12,Inputs!$B$13,0)) -> 440000 | M4: =SUM(C4:L4) -> 2385000
A5: Fruit-bearing | C5: =SUM(Revenue!C8:C14)*(1-IF(1=Inputs!$B$12,Inputs!$B$13,0)) -> 0 | D5: =SUM(Revenue!D8:D14)*(1-IF(2=Inputs!$B$12,Inputs!$B$13,0)) -> 319900 | E5: =SUM(Revenue!E8:E14)*(1-IF(3=Inputs!$B$12,Inputs!$B$13,0)) -> 1399000 | F5: =SUM(Revenue!F8:F14)*(1-IF(4=Inputs!$B$12,Inputs!$B$13,0)) -> 2269000 | G5: =SUM(Revenue!G8:G14)*(1-IF(5=Inputs!$B$12,Inputs!$B$13,0)) -> 3045000 | H5: =SUM(Revenue!H8:H14)*(1-IF(6=Inputs!$B$12,Inputs!$B$13,0)) -> 3760000 | I5: =SUM(Revenue!I8:I14)*(1-IF(7=Inputs!$B$12,Inputs!$B$13,0)) -> 4249000 | J5: =SUM(Revenue!J8:J14)*(1-IF(8=Inputs!$B$12,Inputs!$B$13,0)) -> 4636000 | K5: =SUM(Revenue!K8:K14)*(1-IF(9=Inputs!$B$12,Inputs!$B$13,0)) -> 5024000 | L5: =SUM(Revenue!L8:L14)*(1-IF(10=Inputs!$B$12,Inputs!$B$13,0)) -> 5354000 | M5: =SUM(C5:L5) -> 30055900
A6: Fodder grass | C6: =SUM(Revenue!C15:C15)*(1-IF(1=Inputs!$B$12,Inputs!$B$14,0)) -> 252000 | D6: =SUM(Revenue!D15:D15)*(1-IF(2=Inputs!$B$12,Inputs!$B$14,0)) -> 151200 | E6: =SUM(Revenue!E15:E15)*(1-IF(3=Inputs!$B$12,Inputs!$B$14,0)) -> 396900 | F6: =SUM(Revenue!F15:F15)*(1-IF(4=Inputs!$B$12,Inputs!$B$14,0)) -> 416700 | G6: =SUM(Revenue!G15:G15)*(1-IF(5=Inputs!$B$12,Inputs!$B$14,0)) -> 437580 | H6: =SUM(Revenue!H15:H15)*(1-IF(6=Inputs!$B$12,Inputs!$B$14,0)) -> 459360 | I6: =SUM(Revenue!I15:I15)*(1-IF(7=Inputs!$B$12,Inputs!$B$14,0)) -> 482400 | J6: =SUM(Revenue!J15:J15)*(1-IF(8=Inputs!$B$12,Inputs!$B$14,0)) -> 506520 | K6: =SUM(Revenue!K15:K15)*(1-IF(9=Inputs!$B$12,Inputs!$B$14,0)) -> 531900 | L6: =SUM(Revenue!L15:L15)*(1-IF(10=Inputs!$B$12,Inputs!$B$14,0)) -> 558540 | M6: =SUM(C6:L6) -> 4193100
A7: Medicinal shrubs | C7: =SUM(Revenue!C16:C20)*(1-IF(1=Inputs!$B$12,Inputs!$B$15,0)) -> 52800 | D7: =SUM(Revenue!D16:D20)*(1-IF(2=Inputs!$B$12,Inputs!$B$15,0)) -> 43500 | E7: =SUM(Revenue!E16:E20)*(1-IF(3=Inputs!$B$12,Inputs!$B$15,0)) -> 124500 | F7: =SUM(Revenue!F16:F20)*(1-IF(4=Inputs!$B$12,Inputs!$B$15,0)) -> 132500 | G7: =SUM(Revenue!G16:G20)*(1-IF(5=Inputs!$B$12,Inputs!$B$15,0)) -> 139200 | H7: =SUM(Revenue!H16:H20)*(1-IF(6=Inputs!$B$12,Inputs!$B$15,0)) -> 146100 | I7: =SUM(Revenue!I16:I20)*(1-IF(7=Inputs!$B$12,Inputs!$B$15,0)) -> 153300 | J7: =SUM(Revenue!J16:J20)*(1-IF(8=Inputs!$B$12,Inputs!$B$15,0)) -> 160900 | K7: =SUM(Revenue!K16:K20)*(1-IF(9=Inputs!$B$12,Inputs!$B$15,0)) -> 168900 | L7: =SUM(Revenue!L16:L20)*(1-IF(10=Inputs!$B$12,Inputs!$B$15,0)) -> 177400 | M7: =SUM(C7:L7) -> 1299100
A8: Bamboo | C8: =SUM(Revenue!C21:C21)*(1-IF(1=Inputs!$B$12,Inputs!$B$17,0)) -> 0 | D8: =SUM(Revenue!D21:D21)*(1-IF(2=Inputs!$B$12,Inputs!$B$17,0)) -> 0 | E8: =SUM(Revenue!E21:E21)*(1-IF(3=Inputs!$B$12,Inputs!$B$17,0)) -> 0 | F8: =SUM(Revenue!F21:F21)*(1-IF(4=Inputs!$B$12,Inputs!$B$17,0)) -> 0 | G8: =SUM(Revenue!G21:G21)*(1-IF(5=Inputs!$B$12,Inputs!$B$17,0)) -> 0 | H8: =SUM(Revenue!H21:H21)*(1-IF(6=Inputs!$B$12,Inputs!$B$17,0)) -> 300000 | I8: =SUM(Revenue!I21:I21)*(1-IF(7=Inputs!$B$12,Inputs!$B$17,0)) -> 300000 | J8: =SUM(Revenue!J21:J21)*(1-IF(8=Inputs!$B$12,Inputs!$B$17,0)) -> 300000 | K8: =SUM(Revenue!K21:K21)*(1-IF(9=Inputs!$B$12,Inputs!$B$17,0)) -> 300000 | L8: =SUM(Revenue!L21:L21)*(1-IF(10=Inputs!$B$12,Inputs!$B$17,0)) -> 300000 | M8: =SUM(C8:L8) -> 1500000
A9: Nursery | C9: =SUM(Revenue!C22:C22)*(1-IF(1=Inputs!$B$12,Inputs!$B$16,0)) -> 2475000 | D9: =SUM(Revenue!D22:D22)*(1-IF(2=Inputs!$B$12,Inputs!$B$16,0)) -> 1559250 | E9: =SUM(Revenue!E22:E22)*(1-IF(3=Inputs!$B$12,Inputs!$B$16,0)) -> 2728687.5 | F9: =SUM(Revenue!F22:F22)*(1-IF(4=Inputs!$B$12,Inputs!$B$16,0)) -> 2865121.9 | G9: =SUM(Revenue!G22:G22)*(1-IF(5=Inputs!$B$12,Inputs!$B$16,0)) -> 3008378 | H9: =SUM(Revenue!H22:H22)*(1-IF(6=Inputs!$B$12,Inputs!$B$16,0)) -> 3158796.9 | I9: =SUM(Revenue!I22:I22)*(1-IF(7=Inputs!$B$12,Inputs!$B$16,0)) -> 3316736.7 | J9: =SUM(Revenue!J22:J22)*(1-IF(8=Inputs!$B$12,Inputs!$B$16,0)) -> 3482573.5 | K9: =SUM(Revenue!K22:K22)*(1-IF(9=Inputs!$B$12,Inputs!$B$16,0)) -> 3656702.2 | L9: =SUM(Revenue!L22:L22)*(1-IF(10=Inputs!$B$12,Inputs!$B$16,0)) -> 3839537.3 | M9: =SUM(C9:L9) -> 30090784
A10: Revenue — drought case | C10: =SUM(C4:C9) -> 2819800 | D10: =SUM(D4:D9) -> 2108850 | E10: =SUM(E4:E9) -> 4759087.5 | F10: =SUM(F4:F9) -> 5853321.9 | G10: =SUM(G4:G9) -> 6860158 | H10: =SUM(H4:H9) -> 8104256.9 | I10: =SUM(I4:I9) -> 8821436.7 | J10: =SUM(J4:J9) -> 9445993.5 | ... M10: =SUM(M4:M9) -> 69523884
A11: Operation and maintenance | C11: =CashFlow!C5 -> 4460000 | D11: =CashFlow!D5 -> 4500000 | E11: =CashFlow!E5 -> 4500000 | F11: =CashFlow!F5 -> 4500000 | G11: =CashFlow!G5 -> 4500000 | H11: =CashFlow!H5 -> 4700000 | I11: =CashFlow!I5 -> 4700000 | J11: =CashFlow!J5 -> 4700000 | ... L11: =CashFlow!L5 -> 4700000 | M11: =SUM(C11:L11) -> 45960000
A12: Capital expenditure | C12: =CashFlow!C7 -> 16506000 | D12: =CashFlow!D7 -> 0 | E12: =CashFlow!E7 -> 0 | F12: =CashFlow!F7 -> 0 | G12: =CashFlow!G7 -> 0 | H12: =CashFlow!H7 -> 0 | I12: =CashFlow!I7 -> 0 | J12: =CashFlow!J7 -> 0 | ... L12: =CashFlow!L7 -> 0 | M12: =SUM(C12:L12) -> 16506000
A13: Net cash flow — drought case | C13: =C10-C11-C12 -> -18146200 | D13: =D10-D11-D12 -> -2391150 | E13: =E10-E11-E12 -> 259087.5 | F13: =F10-F11-F12 -> 1353321.9 | G13: =G10-G11-G12 -> 2360158 | H13: =H10-H11-H12 -> 3404256.9 | I13: =I10-I11-I12 -> 4121436.7 | J13: =J10-J11-J12 -> 4745993.5 | ... L13: =L10-L11-L12 -> 5969477.3 | M13: =SUM(C13:L13) -> 7057884
A14: Cumulative — drought case | C14: =C13 -> -18146200 | D14: =C14+D13 -> -20537350 | E14: =D14+E13 -> -20278262 | F14: =E14+F13 -> -18924941 | G14: =F14+G13 -> -16564783 | H14: =G14+H13 -> -13160526 | I14: =H14+I13 -> -9039089.1 | J14: =I14+J13 -> -4293095.5 | K14: =J14+K13 -> 1088406.7 | L14: =K14+L13 -> 7057884
A15: Payback flag (helper) | C15: =IF(C14>=0,1,"") | D15: =IF(AND(D14>=0,C14<0),2,"") | E15: =IF(AND(E14>=0,D14<0),3,"") | F15: =IF(AND(F14>=0,E14<0),4,"") | G15: =IF(AND(G14>=0,F14<0),5,"") | H15: =IF(AND(H14>=0,G14<0),6,"") | I15: =IF(AND(I14>=0,H14<0),7,"") | J15: =IF(AND(J14>=0,I14<0),8,"") | K15: =IF(AND(K14>=0,J14<0),9,"") -> 9 | L15: =IF(AND(L14>=0,K14<0),10,"")
A17: Comparison
A18: Measure | C18: Base case | D18: Drought case | E18: Difference
A19: 10-year revenue | C19: =Revenue!M23 -> 70985784 | D19: =M10 -> 69523884 | E19: =IFERROR(D19-C19,"") -> -1461900
A20: 10-year net position after capital cost | C20: =CashFlow!M8 -> 8519784 | D20: =M13 -> 7057884 | E20: =IFERROR(D20-C20,"") -> -1461900
A21: Payback year | C21: =CashFlow!C18 -> 9 | D21: =IF(COUNT(C15:L15)=0,"Beyond Year 10",MIN(C15:L15)) -> 9 | E21: =IFERROR(D21-C21,"") -> 0

Sheet GrantBudget
A1: CSR grant budget — year one (₹)
A2: Mirrors section 11 of the CSR proposal; lines B and E to be finalised
A3: Ref | B3: Component | C3: Amount (₹) | D3: Note
A4: A | B4: Human capital
A5: A1 | B5: Cadre training — 20 women, five cadres; 10 days a month at ₹500 a day, 12 months | C5: 1200000 | D5: Proposal draft
A6: A2 | B6: Student programme — materials, connectivity, contact sessions, classroom smart devices | C6: 300000 | D6: Proposal draft
A7: A3 | B7: Tutor — 12 months at ₹10,000 a month | C7: 120000 | D7: Proposal draft
A8: A4 | B8: Intern stipends — 5 engineering × ₹5,000 × 12; 5 management × ₹7,000 × 6 | C8: 510000 | D8: Proposal draft
A9: A5 | B9: Master training, exposure visits and cascade training | C9: 300000 | D9: Proposal draft
A10: B | B10: Platform customisation and deployment | D10: To be finalised with VNIT Nagpur
A11: B1 | B11: Katlabodi instance and household identity spine
A12: B2 | B12: VanaGram OS — agroforestry module with document-grounded advisory
A13: B3 | B13: Water module rebuilt for the region
A14: B4 | B14: Health and nutrition module
A15: B5 | B15: Net-zero and carbon revenue module
A16: B6 | B16: Data protection and security layer; Marathi consent workflow
A17: B7 | B17: Open-source release
A18: B8 | B18: Hosting, devices and field connectivity
A19: C | B19: Baselines and project preparation — delivered by the cadre, mentored by UrjaGram | D19: Nil to the grant
A20: D | B20: Project 1 — biodiversity and medicinal agroforestry hub site | D20: Annex D
A21: D1 | B21: Capital expenditure — hub nursery and demonstration site | C21: =Capex!C19 -> 16506000 | D21: Link to Capex sheet
A22: D2 | B22: Year-one operating shortfall | C22: =CashFlow!C13 -> 1640200 | D22: Link to CashFlow sheet
A23: E | B23: Programme management | D23: To be finalised
A24: E1 | B24: Local project manager, field coordination and mobilisation
A25: E2 | B25: Monitoring, documentation and reporting
A26: E3 | B26: Audit and compliance
B28: Subtotal A — human capital | C28: =SUM(C5:C9) -> 2430000
B29: Subtotal B — platform | C29: =SUM(C11:C18) -> 0
B30: Subtotal D — Project 1 | C30: =SUM(C21:C22) -> 18146200
B31: Subtotal E — programme management | C31: =SUM(C24:C26) -> 0
B32: Costed to date (A + D; B and E pending) | C32: =C28+C30 -> 20576200
B33: Total grant sought | C33: =SUM(C28:C31) -> 20576200 | D33: Complete when B and E are costed
